ffpipe/__init__.py
ffpipe/ffpipe.py
ffpipe-0.1.4.dist-info/licenses/LICENSE
ffpipe-0.1.4.dist-info/METADATA
ffpipe-0.1.4.dist-info/WHEEL
ffpipe-0.1.4.dist-info/top_level.txt
ffpipe-0.1.4.dist-info/RECORD
