Metadata-Version: 2.4
Name: ffpipe
Version: 0.1.4
Summary: FFPipe: Image processing in realtime using FFmpeg's pipe mechanism with a robust video/audio sync.
Author: Aryan Shekarlaban
Author-email: arxyzan@gmail.com
License: Apache-2.0
Requires-Python: >=3.10
License-File: LICENSE
Requires-Dist: numpy
Requires-Dist: ffmpeg-python
Requires-Dist: tqdm
Dynamic: author
Dynamic: author-email
Dynamic: description
Dynamic: description-content-type
Dynamic: license
Dynamic: license-file
Dynamic: requires-dist
Dynamic: requires-python
Dynamic: summary
